vcf_stats/__init__.py
vcf_stats/main.py
vcf_stats/processing/__init__.py
vcf_stats/processing/vcf_file_io.py
vcf_stats/processing/vcf_main.py
vcf_stats/processing/vcf_parser.py
vcf_stats/processing/vcf_parser_utils.py
vcf_stats/visualization/__init__.py
vcf_stats/visualization/vcf_web_dashboard.py
vcf_stats/visualization/vcf_web_data.py
vcf_stats/visualization/vcf_web_main.py
vcf_stats/visualization/vcf_web_routes.py
vcf_stats/visualization/vcf_web_templates.py
vcf_stats/visualization/static/dashboard.js
vcf_stats/visualization/templates/index.html
vcf_stats_viz-0.1.1.dist-info/METADATA
vcf_stats_viz-0.1.1.dist-info/WHEEL
vcf_stats_viz-0.1.1.dist-info/entry_points.txt
vcf_stats_viz-0.1.1.dist-info/top_level.txt
vcf_stats_viz-0.1.1.dist-info/RECORD
