Metadata-Version: 2.4
Name: vcf-stats-viz
Version: 0.1.1
Summary: Herramienta para el análisis y visualización de variantes genómicas (VCF) con visualizacion interactiva.
Author-email: Alejandro Lana <alejandrolana1@gmail.com>
License: MIT
Classifier: Programming Language :: Python :: 3.9
Classifier: Topic :: Scientific/Engineering :: Bio-Informatics
Requires-Python: >=3.9
Requires-Dist: pandas
Requires-Dist: dask
Requires-Dist: dask[dataframe]
Requires-Dist: cyvcf2
Requires-Dist: pyarrow
Requires-Dist: fastparquet
Requires-Dist: psutil
Requires-Dist: pysam
Requires-Dist: plotly
Requires-Dist: dash
Requires-Dist: flask
Requires-Dist: matplotlib
Requires-Dist: jinja2
Requires-Dist: weasyprint
Provides-Extra: dev
Requires-Dist: pytest; extra == "dev"
Requires-Dist: black; extra == "dev"
Requires-Dist: jupyterlab; extra == "dev"
